{"title":"Cloud Edge Caching","name":"Acquia:CloudEdgeCaching","class":"\\Drutiny\\Http\\Audit\\HttpHeaderMatch","description":"When Cloudflare is successfully caching a page it will send out `CF-Cache-Status`\nheaders with caching information for the page requested. The value should be **HIT**\n","type":"audit","success":"Acquia Cloud Edge returned with a HIT response.","failure":"Acquia Cloud Edge did not hit cache.\n","remediation":"Please review your Cloud Edge settings to ensure page caching is enabled. Also\ncheck Drupal cache settings to ensure the page requested is cacheable.\n","severity":2,"depends":["HTTP:Cache-Control"]}