{"title":"Boost is not installed","name":"Drupal-8:acquiaBoostDisabled","class":"\\Drutiny\\Plugin\\Drupal8\\Audit\\ModuleDisabled","tags":["Drupal 8","Best Practice","Performance"],"description":"This creates many disk writes, which can cause problems on shared \nservers. See Boost and Acquia Cloud for more details. It is \nrecommended to disable and uninstall this module.\n","remediation":"Disable the Boost module: `drush pm-uninstall boost -y`.\n","success":"The Boost module is not currently enabled.","failure":"The Boost module is currently enabled.","depends":[{"expression":"drupal_module_enabled('boost')","on_fail":"omit"}],"parameters":{"module":{"type":"string","description":"The name of the module to ensure is not installed.","default":"boost"}},"language":"en","type":"audit","signature":"8e5b96904f96876f5b702b93396258208c96f82d"}